Pokemien/__init__.py
Pokemien/pokemon.csv
Pokemien/random_pokemon.py
Pokemien-1.0.1.dist-info/METADATA
Pokemien-1.0.1.dist-info/WHEEL
Pokemien-1.0.1.dist-info/top_level.txt
Pokemien-1.0.1.dist-info/RECORD
